{
  "nfl": {
    "week": 10,
    "games": [
      {
        "matchup": "LV @ DEN",
        "kickoff": "11/6/2025, 7:15:00 PM",
        "status": "Final",
        "score": {
          "home": {
            "name": "DEN",
            "score": "10"
          },
          "away": {
            "name": "LV",
            "score": "7"
          }
        }
      },
      {
        "matchup": "ATL VS IND",
        "kickoff": "11/9/2025, 8:30:00 AM",
        "status": "Scheduled",
        "score": null
      },
      {
        "matchup": "NYG @ CHI",
        "kickoff": "11/9/2025, 12:00:00 PM",
        "status": "Scheduled",
        "score": null
      },
      {
        "matchup": "BUF @ MIA",
        "kickoff": "11/9/2025, 12:00:00 PM",
        "status": "Scheduled",
        "score": null
      },
      {
        "matchup": "BAL @ MIN",
        "kickoff": "11/9/2025, 12:00:00 PM",
        "status": "Scheduled",
        "score": null
      },
      {
        "matchup": "CLE @ NYJ",
        "kickoff": "11/9/2025, 12:00:00 PM",
        "status": "Scheduled",
        "score": null
      },
      {
        "matchup": "NE @ TB",
        "kickoff": "11/9/2025, 12:00:00 PM",
        "status": "Scheduled",
        "score": null
      },
      {
        "matchup": "NO @ CAR",
        "kickoff": "11/9/2025, 12:00:00 PM",
        "status": "Scheduled",
        "score": null
      },
      {
        "matchup": "JAX @ HOU",
        "kickoff": "11/9/2025, 12:00:00 PM",
        "status": "Scheduled",
        "score": null
      },
      {
        "matchup": "ARI @ SEA",
        "kickoff": "11/9/2025, 3:05:00 PM",
        "status": "Scheduled",
        "score": null
      },
      {
        "matchup": "LAR @ SF",
        "kickoff": "11/9/2025, 3:25:00 PM",
        "status": "Scheduled",
        "score": null
      },
      {
        "matchup": "DET @ WSH",
        "kickoff": "11/9/2025, 3:25:00 PM",
        "status": "Scheduled",
        "score": null
      },
      {
        "matchup": "PIT @ LAC",
        "kickoff": "11/9/2025, 7:20:00 PM",
        "status": "Scheduled",
        "score": null
      },
      {
        "matchup": "PHI @ GB",
        "kickoff": "11/10/2025, 7:15:00 PM",
        "status": "Scheduled",
        "score": null
      }
    ]
  },
  "collegeFootball": {
    "games": [
      {
        "matchup": "WAKE @ UVA",
        "kickoff": "11/8/2025, 6:00:00 PM",
        "status": "Final",
        "score": {
          "home": {
            "name": "UVA",
            "score": "9"
          },
          "away": {
            "name": "WAKE",
            "score": "16"
          }
        }
      },
      {
        "matchup": "CAL @ LOU",
        "kickoff": "11/8/2025, 6:00:00 PM",
        "status": "Live: Q4",
        "score": {
          "home": {
            "name": "LOU",
            "score": "23"
          },
          "away": {
            "name": "CAL",
            "score": "23"
          }
        }
      },
      {
        "matchup": "LSU @ ALA",
        "kickoff": "11/8/2025, 6:30:00 PM",
        "status": "Live: Q4",
        "score": {
          "home": {
            "name": "ALA",
            "score": "17"
          },
          "away": {
            "name": "LSU",
            "score": "6"
          }
        }
      },
      {
        "matchup": "NAVY @ ND",
        "kickoff": "11/8/2025, 6:30:00 PM",
        "status": "Live: Q4",
        "score": {
          "home": {
            "name": "ND",
            "score": "49"
          },
          "away": {
            "name": "NAVY",
            "score": "10"
          }
        }
      },
      {
        "matchup": "OSU @ PUR",
        "kickoff": "11/8/2025, 12:00:00 PM",
        "status": "Final",
        "score": {
          "home": {
            "name": "PUR",
            "score": "10"
          },
          "away": {
            "name": "OSU",
            "score": "34"
          }
        }
      },
      {
        "matchup": "IU @ PSU",
        "kickoff": "11/8/2025, 11:00:00 AM",
        "status": "Final",
        "score": {
          "home": {
            "name": "PSU",
            "score": "24"
          },
          "away": {
            "name": "IU",
            "score": "27"
          }
        }
      },
      {
        "matchup": "TA&M @ MIZ",
        "kickoff": "11/8/2025, 2:30:00 PM",
        "status": "Final",
        "score": {
          "home": {
            "name": "MIZ",
            "score": "17"
          },
          "away": {
            "name": "TA&M",
            "score": "38"
          }
        }
      },
      {
        "matchup": "UGA @ MSST",
        "kickoff": "11/8/2025, 11:00:00 AM",
        "status": "Final",
        "score": {
          "home": {
            "name": "MSST",
            "score": "21"
          },
          "away": {
            "name": "UGA",
            "score": "41"
          }
        }
      },
      {
        "matchup": "CIT @ MISS",
        "kickoff": "11/8/2025, 12:00:00 PM",
        "status": "Final",
        "score": {
          "home": {
            "name": "MISS",
            "score": "49"
          },
          "away": {
            "name": "CIT",
            "score": "0"
          }
        }
      },
      {
        "matchup": "BYU @ TTU",
        "kickoff": "11/8/2025, 11:00:00 AM",
        "status": "Final",
        "score": {
          "home": {
            "name": "TTU",
            "score": "29"
          },
          "away": {
            "name": "BYU",
            "score": "7"
          }
        }
      },
      {
        "matchup": "ORE @ IOWA",
        "kickoff": "11/8/2025, 2:30:00 PM",
        "status": "Final",
        "score": {
          "home": {
            "name": "IOWA",
            "score": "16"
          },
          "away": {
            "name": "ORE",
            "score": "18"
          }
        }
      },
      {
        "matchup": "AUB @ VAN",
        "kickoff": "11/8/2025, 3:00:00 PM",
        "status": "Final",
        "score": {
          "home": {
            "name": "VAN",
            "score": "45"
          },
          "away": {
            "name": "AUB",
            "score": "38"
          }
        }
      },
      {
        "matchup": "SYR @ MIA",
        "kickoff": "11/8/2025, 2:30:00 PM",
        "status": "Final",
        "score": {
          "home": {
            "name": "MIA",
            "score": "38"
          },
          "away": {
            "name": "SYR",
            "score": "10"
          }
        }
      },
      {
        "matchup": "WASH @ WIS",
        "kickoff": "11/8/2025, 3:30:00 PM",
        "status": "Final",
        "score": {
          "home": {
            "name": "WIS",
            "score": "13"
          },
          "away": {
            "name": "WASH",
            "score": "10"
          }
        }
      },
      {
        "matchup": "NU @ USC",
        "kickoff": "11/7/2025, 8:00:00 PM",
        "status": "Final",
        "score": {
          "home": {
            "name": "USC",
            "score": "38"
          },
          "away": {
            "name": "NU",
            "score": "17"
          }
        }
      }
    ]
  }
}