{
  "nfl": {
    "week": 12,
    "games": [
      {
        "matchup": "PIT @ CLE",
        "kickoff": "11/21/2024, 7:15:00 PM",
        "status": "Final",
        "score": {
          "home": {
            "name": "CLE",
            "score": "24"
          },
          "away": {
            "name": "PIT",
            "score": "19"
          }
        }
      },
      {
        "matchup": "MIN @ CHI",
        "kickoff": "11/24/2024, 12:00:00 PM",
        "status": "Scheduled",
        "score": null
      },
      {
        "matchup": "DET @ IND",
        "kickoff": "11/24/2024, 12:00:00 PM",
        "status": "Scheduled",
        "score": null
      },
      {
        "matchup": "NE @ MIA",
        "kickoff": "11/24/2024, 12:00:00 PM",
        "status": "Scheduled",
        "score": null
      },
      {
        "matchup": "TB @ NYG",
        "kickoff": "11/24/2024, 12:00:00 PM",
        "status": "Scheduled",
        "score": null
      },
      {
        "matchup": "DAL @ WSH",
        "kickoff": "11/24/2024, 12:00:00 PM",
        "status": "Scheduled",
        "score": null
      },
      {
        "matchup": "KC @ CAR",
        "kickoff": "11/24/2024, 12:00:00 PM",
        "status": "Scheduled",
        "score": null
      },
      {
        "matchup": "TEN @ HOU",
        "kickoff": "11/24/2024, 12:00:00 PM",
        "status": "Scheduled",
        "score": null
      },
      {
        "matchup": "DEN @ LV",
        "kickoff": "11/24/2024, 3:05:00 PM",
        "status": "Scheduled",
        "score": null
      },
      {
        "matchup": "SF @ GB",
        "kickoff": "11/24/2024, 3:25:00 PM",
        "status": "Scheduled",
        "score": null
      },
      {
        "matchup": "ARI @ SEA",
        "kickoff": "11/24/2024, 3:25:00 PM",
        "status": "Scheduled",
        "score": null
      },
      {
        "matchup": "PHI @ LAR",
        "kickoff": "11/24/2024, 7:20:00 PM",
        "status": "Scheduled",
        "score": null
      },
      {
        "matchup": "BAL @ LAC",
        "kickoff": "11/25/2024, 7:15:00 PM",
        "status": "Scheduled",
        "score": null
      }
    ]
  },
  "collegeFootball": {
    "games": [
      {
        "matchup": "MIZ @ MSST",
        "kickoff": "11/23/2024, 3:15:00 PM",
        "status": "Final",
        "score": {
          "home": {
            "name": "MSST",
            "score": "20"
          },
          "away": {
            "name": "MIZ",
            "score": "39"
          }
        }
      },
      {
        "matchup": "ARMY VS ND",
        "kickoff": "11/23/2024, 6:00:00 PM",
        "status": "Live: Q1",
        "score": {
          "home": {
            "name": "ND",
            "score": "13"
          },
          "away": {
            "name": "ARMY",
            "score": "0"
          }
        }
      },
      {
        "matchup": "BOIS @ WYO",
        "kickoff": "11/23/2024, 6:00:00 PM",
        "status": "Live: Q1",
        "score": {
          "home": {
            "name": "WYO",
            "score": "3"
          },
          "away": {
            "name": "BOIS",
            "score": "7"
          }
        }
      },
      {
        "matchup": "IU @ OSU",
        "kickoff": "11/23/2024, 11:00:00 AM",
        "status": "Final",
        "score": {
          "home": {
            "name": "OSU",
            "score": "38"
          },
          "away": {
            "name": "IU",
            "score": "15"
          }
        }
      },
      {
        "matchup": "UK @ TEX",
        "kickoff": "11/23/2024, 2:30:00 PM",
        "status": "Final",
        "score": {
          "home": {
            "name": "TEX",
            "score": "31"
          },
          "away": {
            "name": "UK",
            "score": "14"
          }
        }
      },
      {
        "matchup": "PSU @ MINN",
        "kickoff": "11/23/2024, 2:30:00 PM",
        "status": "Final",
        "score": {
          "home": {
            "name": "MINN",
            "score": "25"
          },
          "away": {
            "name": "PSU",
            "score": "26"
          }
        }
      },
      {
        "matchup": "WAKE @ MIA",
        "kickoff": "11/23/2024, 11:00:00 AM",
        "status": "Final",
        "score": {
          "home": {
            "name": "MIA",
            "score": "42"
          },
          "away": {
            "name": "WAKE",
            "score": "14"
          }
        }
      },
      {
        "matchup": "MISS @ FLA",
        "kickoff": "11/23/2024, 11:00:00 AM",
        "status": "Final",
        "score": {
          "home": {
            "name": "FLA",
            "score": "24"
          },
          "away": {
            "name": "MISS",
            "score": "17"
          }
        }
      },
      {
        "matchup": "MASS @ UGA",
        "kickoff": "11/23/2024, 11:45:00 AM",
        "status": "Final",
        "score": {
          "home": {
            "name": "UGA",
            "score": "59"
          },
          "away": {
            "name": "MASS",
            "score": "21"
          }
        }
      },
      {
        "matchup": "UTEP @ TENN",
        "kickoff": "11/23/2024, 12:00:00 PM",
        "status": "Final",
        "score": {
          "home": {
            "name": "TENN",
            "score": "56"
          },
          "away": {
            "name": "UTEP",
            "score": "0"
          }
        }
      },
      {
        "matchup": "SMU @ UVA",
        "kickoff": "11/23/2024, 11:00:00 AM",
        "status": "Final",
        "score": {
          "home": {
            "name": "UVA",
            "score": "7"
          },
          "away": {
            "name": "SMU",
            "score": "33"
          }
        }
      },
      {
        "matchup": "BYU @ ASU",
        "kickoff": "11/23/2024, 2:30:00 PM",
        "status": "Final",
        "score": {
          "home": {
            "name": "ASU",
            "score": "28"
          },
          "away": {
            "name": "BYU",
            "score": "23"
          }
        }
      },
      {
        "matchup": "COLO @ KU",
        "kickoff": "11/23/2024, 2:30:00 PM",
        "status": "Final",
        "score": {
          "home": {
            "name": "KU",
            "score": "37"
          },
          "away": {
            "name": "COLO",
            "score": "21"
          }
        }
      },
      {
        "matchup": "CIT @ CLEM",
        "kickoff": "11/23/2024, 2:30:00 PM",
        "status": "Final",
        "score": {
          "home": {
            "name": "CLEM",
            "score": "51"
          },
          "away": {
            "name": "CIT",
            "score": "14"
          }
        }
      },
      {
        "matchup": "WOF @ SC",
        "kickoff": "11/23/2024, 3:00:00 PM",
        "status": "Final",
        "score": {
          "home": {
            "name": "SC",
            "score": "56"
          },
          "away": {
            "name": "WOF",
            "score": "12"
          }
        }
      },
      {
        "matchup": "ILL @ RUTG",
        "kickoff": "11/23/2024, 11:00:00 AM",
        "status": "Final",
        "score": {
          "home": {
            "name": "RUTG",
            "score": "31"
          },
          "away": {
            "name": "ILL",
            "score": "38"
          }
        }
      },
      {
        "matchup": "ALA @ OU",
        "kickoff": "11/23/2024, 6:30:00 PM",
        "status": "Scheduled",
        "score": null
      },
      {
        "matchup": "TA&M @ AUB",
        "kickoff": "11/23/2024, 6:30:00 PM",
        "status": "Scheduled",
        "score": null
      },
      {
        "matchup": "ISU @ UTAH",
        "kickoff": "11/23/2024, 6:30:00 PM",
        "status": "Scheduled",
        "score": null
      },
      {
        "matchup": "UNLV @ SJSU",
        "kickoff": "11/22/2024, 9:00:00 PM",
        "status": "Final",
        "score": {
          "home": {
            "name": "SJSU",
            "score": "16"
          },
          "away": {
            "name": "UNLV",
            "score": "27"
          }
        }
      }
    ]
  }
}